<?xml version="1.0" encoding="UTF-8"?>
<!DOCTYPE DOKUMENT SYSTEM "BUNDESTAGSDOKUMENTE.dtd">
<DOKUMENT>
  <WAHLPERIODE>9</WAHLPERIODE>
  <DOKUMENTART>DRUCKSACHE</DOKUMENTART>
  <DRS_TYP>Antrag</DRS_TYP>
  <NR>09/53</NR>
  <DATUM>18.12.1980</DATUM>
  <TITEL>Wahl der Vertreter der Bundesrepublik Deutschland in der Parlamentarischen Versammlung des Europarats</TITEL>
  <K_URHEBER>Fraktion der CDU/CSU</K_URHEBER>
  <K_URHEBER>Fraktion der FDP</K_URHEBER>
  <K_URHEBER>Fraktion der SPD</K_URHEBER>
  <TEXT>Deutscher Bundestag 9. Wahlperiode
Drucksache 9/53
18.12.80 Sachgebiet 111 
Antrag
der Fraktionen der CDU/CSU, SPD und FDP
Wahl der Vertreter der Bundesrepublik Deutschland in der Parlamentarischen Versammlung des Europarats
Der Bundestag wolle beschließen:
Als Vertreter der Bundesrepublik Deutschland in der Parlamentarischen Versammlung des Europarats und als ihre Stellvertreter gemäß §§ 1 und 2 des Gesetzes über die Wahl der Vertreter der Bundesrepublik zur Beratenden Versammlung des Europarats vom 11. Juni 1951 (BGBl. I S. 397), geändert durch Gesetz vom 4. August 1953 (BGBl. I S. 779), werden die folgenden Abgeordneten gewählt:
Mitglieder CDU/CSU
Dr. Althammer
Böhm (Melsungen)
Kittelmann Dr. Müller Reddemann
Dr. Freiherr Spies von Büllesheim Dr. Sprung
Dr. Unland
SPD
Dr. Ahrens Dr. Bardens Büchner (Speyer)
Dr. Enders Dr. Geßner Männing
Schmidt (Würgendorf)
Schulte (Unna)
Stellvertreter CDU/CSU
Amrehn
Jäger (Wangen) Lemmrich
Lenzer
Müller (Wadern) Frau Pack
Dr. Schäuble
Dr. Wittmann
SPD
Bahr
Dr. Corterier
Eickmeyer
Dr. Holtz
Horn Pensky
Schmidt (München) Topmann

FDP
Jung (Kandel) Dr. Vohrer
Bonn, den 18. Dezember 1980
FDP
Schmidt (Kempten) Rösch
Dr. Kohl, Dr. Zimmermann und Fraktion Wehner und Fraktion
Mischnick und Fraktion</TEXT>
</DOKUMENT>
