<?xml version="1.0" encoding="UTF-8"?>
<!DOCTYPE DOKUMENT SYSTEM "BUNDESTAGSDOKUMENTE.dtd">
<DOKUMENT>
  <WAHLPERIODE>9</WAHLPERIODE>
  <DOKUMENTART>DRUCKSACHE</DOKUMENTART>
  <DRS_TYP>Beschlussempfehlung</DRS_TYP>
  <NR>09/2287</NR>
  <DATUM>10.12.1982</DATUM>
  <TITEL>zu der Unterrichtung durch die Bundesregierung - Drucksache 9/1921 - Der Finanzplan des Bundes 1982 bis 1986</TITEL>
  <K_URHEBER>Haushaltsausschuss</K_URHEBER>
  <TEXT>Deutscher Bundestag 9. Wahlperiode
Drucksache 9/2287
10.12.82 Sachgebiet 63 
Beschlußempfehlung
des Haushaltsausschusses (8. Ausschuß)
zu der Unterrichtung durch die Bundesregierung - Drucksache 9/1921 -
Der Finanzplan des Bundes 1982 bis 1986
Der Bundestag wolle beschließen,
von der Unterrichtung durch die Bundesregierung in der Drucksache 9/1921 zum Finanzplan des Bundes 1982 bis 1986 Kenntnis zu nehmen.
Bonn, den 10. Dezember 1982
Der Haushaltsausschuß
Esters Vorsitzender
Hoppe
Berichterstatter
Dr. Riedl (München)</TEXT>
</DOKUMENT>
